[
    {
        "title": "Test Title",
        "description": "vfvnfuibvn hfuhuifghfyud hfudsgfyvbhv hfugfydsgbvufv  h dvb hv uifhvfvvbfivb vfvhfv h  fdffdhf  jfdhfudhvv  iffhdihvfbfvu  u hgu huhgvfnbjfhgurhgrul g fghughur;ghhgfblfzhjhjdiiusyehf jjhfhur fhfdfbueuisih hfelfbu.",
        "datePosted": "2-5-2000",
        "userName": "akdd2"
    },
    {
        "title": "Test Title2",
        "description": "vfvnfuibvn hfuhuifghfyud hfudsgfyvbhv hfugfydsgbvufv  h dvb hv uifhvfvvbfivb vfvhfv h dv nv  mffng gd fdffdhf  jfdhfudhvv  iffhdihvfbfvu  u hgu huhgvfnbjfhgurhgrul g fghughur;ghhgfblfzhjhjdiiusyehf jjhfhur fhfdfbueuisih hfelfbu.",
        "datePosted": "2-8-2000",
        "userName": "davidd55d"
    },
    {
        "title": "Test Title3",
        "description": "vfvnfuibvn hfuhuifghfyud hfudsgfyvbhv hfugfydsgbvufv  h dvb hv uifhvfvvbfivb vfvhfv h  fdffdhf  jfdhfudhvv hfelfbu.",
        "datePosted": "2-5-2001",
        "userName": "starrz"
    }
]